panqc/__init__.py
panqc/_version.py
panqc/asm_gene_search.py
panqc/ava.py
panqc/kmerlib.py
panqc/nscluster.py
panqc/utils.py
panqc-0.0.4.dist-info/METADATA
panqc-0.0.4.dist-info/WHEEL
panqc-0.0.4.dist-info/entry_points.txt
panqc-0.0.4.dist-info/licenses/LICENSE
panqc-0.0.4.dist-info/RECORD
