Metadata-Version: 2.1
Name: panqc
Version: 0.0.4
Summary: Package & software for analysis of nucleotide redundancy within CDS-based pan-genome analyses
Project-URL: Homepage, https://github.com/maxgmarin/panqc
Author-email: Maximillian Marin <maximilliangmarin@gmail.com>
License-File: LICENSE
Requires-Python: >=3.7
Requires-Dist: colored
Requires-Dist: importlib-metadata; python_version < '3.8'
Requires-Dist: mappy==2.26
Requires-Dist: mmh3
Requires-Dist: networkx
Requires-Dist: pandas
Requires-Dist: screed
Requires-Dist: tqdm
Provides-Extra: test
Requires-Dist: pytest; extra == 'test'
